clara_imaging_algos-0.0.12.data/purelib/clara/imaging/__init__.py
clara_imaging_algos-0.0.12.data/purelib/clara/imaging/algos.so
clara_imaging_algos-0.0.12.data/purelib/clara/imaging/libMDCTBone.so
clara_imaging_algos-0.0.12.data/purelib/clara/imaging/libMDImaging.so
clara_imaging_algos-0.0.12.dist-info/DESCRIPTION.rst
clara_imaging_algos-0.0.12.dist-info/METADATA
clara_imaging_algos-0.0.12.dist-info/RECORD
clara_imaging_algos-0.0.12.dist-info/WHEEL
clara_imaging_algos-0.0.12.dist-info/metadata.json
clara_imaging_algos-0.0.12.dist-info/top_level.txt
