Metadata-Version: 2.0
Name: clara-imaging-algos
Version: 0.0.12
Summary: Clara Imaging Algorithms
Home-page: UNKNOWN
Author: NVIDIA Corporation
License: UNKNOWN
Platform: UNKNOWN
Requires-Python: >=3.8
Requires-Dist: patchelf
